{"type": "Feature", "id": 12523235, "geometry": {"type": "Point", "coordinates": [26.75, -22.41667]}, "properties": {"woe:id": 12523235, "woe:parent_id": 1265886, "woe:name": "Serowe Airport", "woe:placetype": 14, "woe:placetype_name": "Airport", "woe:lang": "ENG", "iso:country": "BW", "meta:provider": ["geoplanet:7.3.1", "geoplanet:7.3.2", "geoplanet:7.4.0", "geoplanet:7.4.1", "geoplanet:7.5.1", "geoplanet:7.5.2", "geoplanet:7.6.0", "geoplanet:7.8.1", "geoplanet:7.9.0", "geoplanet:7.10.0", "geoplanet:8.0.0", "woeplanet:8.0.0"], "meta:indexed": "2020-08-20T20:52:00.429873", "meta:updated": "2020-10-14T11:16:42.152826", "woe:hierarchy": {"continent": 24865670, "country": 23424755, "town": 0, "planet": 1, "county": 0, "suburb": 0, "state": 2344741, "region": 0, "localadmin": 0}, "woe:timezone_id": 28350702, "woe:hash": "ks502xnv2jvd", "woe:centroid": [26.75, -22.41667], "geom:latitude": -22.41667, "geom:longitude": 26.75, "geom:hash": "ks502xnv2jvd", "woe:latitude": -22.41667, "geom:centroid": [26.75, -22.41667], "woe:longitude": 26.75, "woe:repo": "woeplanet-airport-bw", "geom:area": 0.0, "woe:scale": 19}}